igvf_client/__init__.py
igvf_client/api_client.py
igvf_client/api_response.py
igvf_client/configuration.py
igvf_client/exceptions.py
igvf_client/py.typed
igvf_client/rest.py
igvf_client/api/__init__.py
igvf_client/api/igvf_api.py
igvf_client/models/__init__.py
igvf_client/models/access_key.py
igvf_client/models/access_key_results.py
igvf_client/models/alignment_file.py
igvf_client/models/alignment_file_results.py
igvf_client/models/analysis_set.py
igvf_client/models/analysis_set_results.py
igvf_client/models/analysis_step.py
igvf_client/models/analysis_step_results.py
igvf_client/models/analysis_step_version.py
igvf_client/models/analysis_step_version_results.py
igvf_client/models/assay_term.py
igvf_client/models/assay_term_results.py
igvf_client/models/atac_bam_summary_stats.py
igvf_client/models/atac_fragment_summary_stats.py
igvf_client/models/atac_fragments_alignment_stats.py
igvf_client/models/attachment.py
igvf_client/models/attachment1.py
igvf_client/models/auxiliary_set.py
igvf_client/models/auxiliary_set_results.py
igvf_client/models/award.py
igvf_client/models/award_results.py
igvf_client/models/biomarker.py
igvf_client/models/biomarker_results.py
igvf_client/models/configuration_file.py
igvf_client/models/configuration_file_results.py
igvf_client/models/construct_library_set.py
igvf_client/models/construct_library_set_results.py
igvf_client/models/crispr_modification.py
igvf_client/models/crispr_modification_results.py
igvf_client/models/curated_set.py
igvf_client/models/curated_set_results.py
igvf_client/models/degron_modification.py
igvf_client/models/degron_modification_results.py
igvf_client/models/document.py
igvf_client/models/document_results.py
igvf_client/models/gene.py
igvf_client/models/gene_location.py
igvf_client/models/gene_location1.py
igvf_client/models/gene_results.py
igvf_client/models/genome_browser_annotation_file.py
igvf_client/models/genome_browser_annotation_file_results.py
igvf_client/models/human_donor.py
igvf_client-107.0.1.dist-info/licenses/LICENSE
igvf_client-107.0.1.dist-info/METADATA
igvf_client-107.0.1.dist-info/WHEEL
igvf_client-107.0.1.dist-info/top_level.txt
igvf_client-107.0.1.dist-info/RECORD
