Metadata-Version: 2.4
Name: igvf-client
Version: 107.0.1
Summary: IGVF Project API
Home-page: https://github.com/iGVF-DACC/igvf-python-client
Author: IGVF DACC
Author-email: encode-help@lists.stanford.edu
Keywords: OpenAPI,OpenAPI-Generator,IGVF Project API
License-File: LICENSE
Requires-Dist: urllib3<2.1.0,>=1.25.3
Requires-Dist: python-dateutil
Requires-Dist: pydantic>=2
Requires-Dist: typing-extensions>=4.7.1
Dynamic: author
Dynamic: author-email
Dynamic: description
Dynamic: description-content-type
Dynamic: home-page
Dynamic: keywords
Dynamic: license-file
Dynamic: requires-dist
Dynamic: summary
